app/__init__.py
app/assets/__init__.py
app/assets/subdomains.py
app/config/__init__.py
app/config/config_loader.py
app/src/__init__.py
app/src/main.py
dns_guesser-0.1.6.dist-info/LICENSE
dns_guesser-0.1.6.dist-info/METADATA
dns_guesser-0.1.6.dist-info/WHEEL
dns_guesser-0.1.6.dist-info/entry_points.txt
dns_guesser-0.1.6.dist-info/top_level.txt
dns_guesser-0.1.6.dist-info/RECORD
