Metadata-Version: 2.2
Name: dns-guesser
Version: 0.1.6
Requires-Python: >=3.10
License-File: LICENSE
Requires-Dist: dnspython==2.7.0
Dynamic: description
Dynamic: description-content-type
Dynamic: requires-dist
Dynamic: requires-python
